<?xml version="1.0" encoding="UTF-8"?>
<!DOCTYPE score-partwise PUBLIC "-//Recordare//DTD MusicXML 2.0 Partwise//EN"
                                "http://www.musicxml.org/dtds/partwise.dtd">
<score-partwise version="3.0">
  <identification>
    <encoding>
      <software>Frescobaldi 2.18.1</software>
      <encoding-date>2016-12-04</encoding-date>
    </encoding>
  </identification>
  <part-list>
    <score-part id="P1">
      <part-name />
    </score-part>
  </part-list>
  <part id="P1">
    <measure number="1">
      <attributes>
        <divisions>8</divisions>
        <time>
          <beats>12</beats>
          <beat-type>1</beat-type>
        </time>
        <clef>
          <sign>G</sign>
          <line>2</line>
        </clef>
      </attributes>
      <note>
        <pitch>
          <step>C</step>
          <octave>6</octave>
        </pitch>
        <duration>384</duration>
        <voice>1</voice>
        <type>maxima</type>
        <dot />
      </note>
    </measure>
    <measure number="2">
      <note>
        <pitch>
          <step>C</step>
          <octave>6</octave>
        </pitch>
        <duration>192</duration>
        <voice>1</voice>
        <type>long</type>
        <dot />
      </note>
    </measure>
    <measure number="3">
      <note>
        <pitch>
          <step>C</step>
          <octave>6</octave>
        </pitch>
        <duration>192</duration>
        <voice>1</voice>
        <type>long</type>
        <dot />
      </note>
    </measure>
    <measure number="4">
      <note>
        <pitch>
          <step>C</step>
          <octave>6</octave>
        </pitch>
        <duration>96</duration>
        <voice>1</voice>
        <type>breve</type>
        <dot />
      </note>
      <note>
        <pitch>
          <step>C</step>
          <octave>6</octave>
        </pitch>
        <duration>48</duration>
        <voice>1</voice>
        <type>whole</type>
        <dot />
      </note>
      <note>
        <pitch>
          <step>C</step>
          <octave>6</octave>
        </pitch>
        <duration>24</duration>
        <voice>1</voice>
        <type>half</type>
        <dot />
      </note>
      <note>
        <pitch>
          <step>C</step>
          <octave>6</octave>
        </pitch>
        <duration>12</duration>
        <voice>1</voice>
        <type>quarter</type>
        <dot />
      </note>
      <note>
        <pitch>
          <step>C</step>
          <octave>6</octave>
        </pitch>
        <duration>6</duration>
        <voice>1</voice>
        <type>eighth</type>
        <dot />
      </note>
      <note>
        <pitch>
          <step>C</step>
          <octave>6</octave>
        </pitch>
        <duration>3</duration>
        <voice>1</voice>
        <type>16th</type>
        <dot />
      </note>
      <note>
        <pitch>
          <step>D</step>
          <octave>6</octave>
        </pitch>
        <duration>3</duration>
        <voice>1</voice>
        <type>16th</type>
        <dot />
      </note>
    </measure>
    <measure number="5">
      <note>
        <pitch>
          <step>C</step>
          <octave>6</octave>
        </pitch>
        <duration>96</duration>
        <voice>1</voice>
        <type>breve</type>
        <dot />
      </note>
      <note>
        <pitch>
          <step>C</step>
          <octave>6</octave>
        </pitch>
        <duration>48</duration>
        <voice>1</voice>
        <type>whole</type>
        <dot />
      </note>
      <note>
        <pitch>
          <step>C</step>
          <octave>6</octave>
        </pitch>
        <duration>24</duration>
        <voice>1</voice>
        <type>half</type>
        <dot />
      </note>
      <note>
        <pitch>
          <step>C</step>
          <octave>6</octave>
        </pitch>
        <duration>12</duration>
        <voice>1</voice>
        <type>quarter</type>
        <dot />
      </note>
      <note>
        <pitch>
          <step>C</step>
          <octave>6</octave>
        </pitch>
        <duration>6</duration>
        <voice>1</voice>
        <type>eighth</type>
        <dot />
      </note>
      <note>
        <pitch>
          <step>C</step>
          <octave>6</octave>
        </pitch>
        <duration>3</duration>
        <voice>1</voice>
        <type>16th</type>
        <dot />
      </note>
      <note>
        <pitch>
          <step>D</step>
          <octave>6</octave>
        </pitch>
        <duration>3</duration>
        <voice>1</voice>
        <type>16th</type>
        <dot />
      </note>
    </measure>
    <measure number="6">
      <barline location="right">
        <bar-style>light-heavy</bar-style>
      </barline>
    </measure>
    <measure number="7" />
  </part>
</score-partwise>
