<?xml version="1.0" encoding="UTF-8" standalone="no"?>
<!DOCTYPE score-partwise PUBLIC "-//Recordare//DTD MusicXML 2.0 Partwise//EN" "http://www.musicxml.org/dtds/partwise.dtd">
<score-partwise version="2.0">
 <work>
 <work>
  <work-title>BANA 2015 Example 3.2.2-1: Octave signs</work-title>
 </work>
 </work>
 <identification>
  <creator type="composer"></creator>
  <creator type="poet"></creator>
  <rights>(a)</rights>
  <encoding>
   <software>Neuratron PhotoScore</software>
   <encoding-description>MusicXML 2.0</encoding-description>
  </encoding>
  <source>Scanned sheet music</source>
 </identification>
 <defaults>
  <scaling>
   <millimeters>60</millimeters>
   <tenths>400</tenths>
  </scaling>
  <page-layout>
   <page-height>420</page-height>
   <page-width>926</page-width>
  </page-layout>
 </defaults>
 <part-list>
  <score-part id="P1">
   <part-name></part-name>
   <part-abbreviation></part-abbreviation>
   <score-instrument id="P1-I1">
    <instrument-name></instrument-name>
   </score-instrument>
   <midi-instrument id="P1-I1">
    <midi-channel>1</midi-channel>
    <midi-program>1</midi-program>
   </midi-instrument>
  </score-part>
 </part-list>
 <part id="P1">
  <measure number="1">
   <attributes>
    <divisions>2</divisions>
    <time>
     <beats>6</beats>
     <beat-type>8</beat-type>
    </time>
    <clef number="1">
     <sign>G</sign>
     <line>2</line>
    </clef>
   </attributes>
    <direction placement="below">
      <direction-type>
        <words default-y="-73" font-style="italic" relative-x="5"
        font-size="10.5" font-weight="bold" xml:lang="fr">(a)</words>
      </direction-type>
    </direction>
   <note>
    <pitch>
     <step>C</step>
     <octave>5</octave>
    </pitch>
    <duration>1</duration>
    <voice>1</voice>
    <type>eighth</type>
    <stem>down</stem>
    <beam number="1">begin</beam>
   </note>
   <note>
    <pitch>
     <step>B</step>
     <octave>4</octave>
    </pitch>
    <duration>1</duration>
    <voice>1</voice>
    <type>eighth</type>
    <stem>down</stem>
    <beam number="1">continue</beam>
   </note>
   <note>
    <pitch>
     <step>A</step>
     <octave>4</octave>
    </pitch>
    <duration>1</duration>
    <voice>1</voice>
    <type>eighth</type>
    <stem>down</stem>
    <beam number="1">end</beam>
   </note>
   <note>
    <pitch>
     <step>G</step>
     <octave>4</octave>
    </pitch>
    <duration>1</duration>
    <voice>1</voice>
    <type>eighth</type>
    <stem>up</stem>
    <beam number="1">begin</beam>
   </note>
   <note>
    <pitch>
     <step>E</step>
     <octave>4</octave>
    </pitch>
    <duration>1</duration>
    <voice>1</voice>
    <type>eighth</type>
    <stem>up</stem>
    <beam number="1">continue</beam>
   </note>
   <note>
    <pitch>
     <step>F</step>
     <octave>4</octave>
    </pitch>
    <duration>1</duration>
    <voice>1</voice>
    <type>eighth</type>
    <stem>up</stem>
    <beam number="1">end</beam>
   </note>
  </measure>
  <measure number="2">
    <direction placement="below">
      <direction-type>
        <words default-y="-73" font-style="italic" relative-x="5"
        font-size="10.5" font-weight="bold" xml:lang="fr">(b)</words>
      </direction-type>
    </direction>
   <note>
    <pitch>
     <step>D</step>
     <octave>4</octave>
    </pitch>
    <duration>1</duration>
    <voice>1</voice>
    <type>eighth</type>
    <stem>up</stem>
    <beam number="1">begin</beam>
   </note>
   <note>
    <pitch>
     <step>B</step>
     <octave>4</octave>
    </pitch>
    <duration>1</duration>
    <voice>1</voice>
    <type>eighth</type>
    <stem>up</stem>
    <beam number="1">continue</beam>
   </note>
   <note>
    <pitch>
     <step>A</step>
     <octave>4</octave>
    </pitch>
    <duration>1</duration>
    <voice>1</voice>
    <type>eighth</type>
    <stem>up</stem>
    <beam number="1">end</beam>
   </note>
   <note>
    <pitch>
     <step>G</step>
     <octave>5</octave>
    </pitch>
    <duration>1</duration>
    <voice>1</voice>
    <type>eighth</type>
    <stem>down</stem>
    <beam number="1">begin</beam>
   </note>
   <note>
    <pitch>
     <step>F</step>
     <octave>5</octave>
    </pitch>
    <duration>1</duration>
    <voice>1</voice>
    <type>eighth</type>
    <stem>down</stem>
    <beam number="1">continue</beam>
   </note>
   <note>
    <pitch>
     <step>A</step>
     <octave>4</octave>
    </pitch>
    <duration>1</duration>
    <voice>1</voice>
    <type>eighth</type>
    <stem>down</stem>
    <beam number="1">end</beam>
   </note>
  </measure>
  <measure number="3">
    <direction placement="below">
      <direction-type>
        <words default-y="-73" font-style="italic" relative-x="5"
        font-size="10.5" font-weight="bold" xml:lang="fr">(c)</words>
      </direction-type>
    </direction>
   <note>
    <pitch>
     <step>C</step>
     <octave>5</octave>
    </pitch>
    <duration>1</duration>
    <voice>1</voice>
    <type>eighth</type>
    <stem>up</stem>
    <beam number="1">begin</beam>
   </note>
   <note>
    <pitch>
     <step>F</step>
     <octave>4</octave>
    </pitch>
    <duration>1</duration>
    <voice>1</voice>
    <type>eighth</type>
    <stem>up</stem>
    <beam number="1">continue</beam>
   </note>
   <note>
    <pitch>
     <step>G</step>
     <octave>4</octave>
    </pitch>
    <duration>1</duration>
    <voice>1</voice>
    <type>eighth</type>
    <stem>up</stem>
    <beam number="1">end</beam>
   </note>
   <note>
    <pitch>
     <step>D</step>
     <octave>4</octave>
    </pitch>
    <duration>1</duration>
    <voice>1</voice>
    <type>eighth</type>
    <stem>up</stem>
    <beam number="1">begin</beam>
   </note>
   <note>
    <pitch>
     <step>A</step>
     <octave>4</octave>
    </pitch>
    <duration>1</duration>
    <voice>1</voice>
    <type>eighth</type>
    <stem>up</stem>
    <beam number="1">continue</beam>
   </note>
   <note>
    <pitch>
     <step>D</step>
     <octave>5</octave>
    </pitch>
    <duration>1</duration>
    <voice>1</voice>
    <type>eighth</type>
    <stem>up</stem>
    <beam number="1">end</beam>
   </note>
  </measure>
  <measure number="4">
   <note>
    <pitch>
     <step>C</step>
     <octave>5</octave>
    </pitch>
    <duration>2</duration>
    <voice>1</voice>
    <type>quarter</type>
    <stem>down</stem>
   </note>
   <note>
    <pitch>
     <step>C</step>
     <octave>4</octave>
    </pitch>
    <duration>1</duration>
    <voice>1</voice>
    <type>eighth</type>
    <stem>up</stem>
   </note>
   <note>
    <pitch>
     <step>C</step>
     <octave>4</octave>
    </pitch>
    <duration>3</duration>
    <voice>1</voice>
    <type>quarter</type>
    <dot/>
    <stem>up</stem>
   </note>
   <barline location="right">
    <bar-style>light-light</bar-style>
   </barline>
  </measure>
 </part>
</score-partwise>
